bugasura/__init__.py
bugasura/check_version.py
bugasura/cli.py
bugasura/config.py
bugasura/uploader.py
bugasura-0.0.3.dist-info/METADATA
bugasura-0.0.3.dist-info/WHEEL
bugasura-0.0.3.dist-info/entry_points.txt
bugasura-0.0.3.dist-info/top_level.txt
bugasura-0.0.3.dist-info/RECORD
